fcoclient/__init__.py
fcoclient/cli.py
fcoclient/client.py
fcoclient/config.py
fcoclient/exceptions.py
fcoclient/utils.py
fcoclient/commands/__init__.py
fcoclient/commands/base.py
fcoclient/commands/configure.py
fcoclient/commands/disk.py
fcoclient/commands/firewalltemplate.py
fcoclient/commands/image.py
fcoclient/commands/job.py
fcoclient/commands/network.py
fcoclient/commands/nic.py
fcoclient/commands/productoffer.py
fcoclient/commands/server.py
fcoclient/commands/sshkey.py
fcoclient/commands/vdc.py
fcoclient/resources/__init__.py
fcoclient/resources/base.py
fcoclient/resources/disk.py
fcoclient/resources/firewalltemplate.py
fcoclient/resources/image.py
fcoclient/resources/job.py
fcoclient/resources/network.py
fcoclient/resources/nic.py
fcoclient/resources/productoffer.py
fcoclient/resources/server.py
fcoclient/resources/sshkey.py
fcoclient/resources/vdc.py
fcoclient-0.3.2.dist-info/DESCRIPTION.rst
fcoclient-0.3.2.dist-info/METADATA
fcoclient-0.3.2.dist-info/RECORD
fcoclient-0.3.2.dist-info/WHEEL
fcoclient-0.3.2.dist-info/entry_points.txt
fcoclient-0.3.2.dist-info/metadata.json
fcoclient-0.3.2.dist-info/pbr.json
fcoclient-0.3.2.dist-info/top_level.txt
